fdicdata/__init__.py
fdicdata/dataTaxonomy.py
fdicdata/getFailures.py
fdicdata/getFinancials.py
fdicdata/getHistory.py
fdicdata/getInstitution.py
fdicdata/getInstitutionsAll.py
fdicdata/getLocation.py
fdicdata/getSummary.py
fdicdata/getTaxonomy.py
fdicdata-0.1.7.dist-info/METADATA
fdicdata-0.1.7.dist-info/WHEEL
fdicdata-0.1.7.dist-info/top_level.txt
fdicdata-0.1.7.dist-info/RECORD
